nlpannotator/__init__.py
nlpannotator/base.py
nlpannotator/install_treetagger.py
nlpannotator/main.py
nlpannotator/mflair.py
nlpannotator/msomajo.py
nlpannotator/mspacy.py
nlpannotator/mstanza.py
nlpannotator/mtreetagger.py
nlpannotator/pipe.py
nlpannotator-1.0.6.dist-info/LICENSE
nlpannotator-1.0.6.dist-info/METADATA
nlpannotator-1.0.6.dist-info/WHEEL
nlpannotator-1.0.6.dist-info/entry_points.txt
nlpannotator-1.0.6.dist-info/top_level.txt
nlpannotator-1.0.6.dist-info/RECORD
