Metadata-Version: 2.1
Name: nlpannotator
Version: 1.0.6
Summary: Annotator combining different NLP pipelines
Maintainer-email: Inga Ulusoy <ssc@iwr.uni-heidelberg.de>
License: MIT
Classifier: Programming Language :: Python :: 3
Classifier: Operating System :: OS Independent
Classifier: License :: OSI Approved :: MIT License
Requires-Python: <4,>=3.7
License-File: LICENSE
Requires-Dist: spacy <3.5.0,>=3.4.0
Requires-Dist: stanza <=1.4.0
Requires-Dist: flair <=0.11.3
Requires-Dist: SoMaJo
Requires-Dist: treetaggerwrapper
Requires-Dist: jsonschema
Requires-Dist: importlib-resources >=5.8
Requires-Dist: pytorch !=1.8,>=1.5.0
